rllite/__init__.py
rllite/A2C/A2C.py
rllite/A2C/__init__.py
rllite/A3C/__init__.py
rllite/ACER/ACER.py
rllite/ACER/__init__.py
rllite/ACKTR/__init__.py
rllite/Base/Base.py
rllite/Base/__init__.py
rllite/CategoricalDQN/CategoricalDQN.py
rllite/CategoricalDQN/__init__.py
rllite/DDPG/DDPG.py
rllite/DDPG/__init__.py
rllite/DQN/DQN.py
rllite/DQN/__init__.py
rllite/DQN/utils.py
rllite/DoubleDQN/DoubleDQN.py
rllite/DoubleDQN/__init__.py
rllite/DoubleDQN/utils.py
rllite/DuelingDQN/DuelingDQN.py
rllite/DuelingDQN/__init__.py
rllite/GAIL/GAIL.py
rllite/GAIL/__init__.py
rllite/HER/HER.py
rllite/HER/__init__.py
rllite/HierarchicalDQN/HierarchicalDQN.py
rllite/HierarchicalDQN/__init__.py
rllite/NAF/__init__.py
rllite/NoisyDQN/NoisyDQN.py
rllite/NoisyDQN/__init__.py
rllite/PG/PG.py
rllite/PG/__init__.py
rllite/PPO/PPO.py
rllite/PPO/__init__.py
rllite/PrioritizedDQN/PrioritizedDQN.py
rllite/PrioritizedDQN/__init__.py
rllite/QuantileRegressionDQN/QuantileRegressionDQN.py
rllite/QuantileRegressionDQN/__init__.py
rllite/RainbowDQN/RainbowDQN.py
rllite/RainbowDQN/__init__.py
rllite/SAC/SAC.py
rllite/SAC/__init__.py
rllite/SQL/SQL.py
rllite/SQL/__init__.py
rllite/SQL/policynet.py
rllite/SQL/qnet.py
rllite/SQL/softqlearning.py
rllite/SQL/env/__init__.py
rllite/SQL/env/controller.py
rllite/SQL/env/terrain.py
rllite/TD3/TD3.py
rllite/TD3/__init__.py
rllite/TRPO/__init__.py
rllite/TRPO/conjugate_gradients.py
rllite/TRPO/main.py
rllite/TRPO/models.py
rllite/TRPO/replay_memory.py
rllite/TRPO/running_state.py
rllite/TRPO/trpo.py
rllite/TRPO/utils.py
rllite/common/__init__.py
rllite/common/gym_utils.py
rllite/common/noise.py
rllite/common/plot.py
rllite/common/policy.py
rllite/common/replay_buffer.py
rllite/common/train.py
rllite/common/vec_env.py
rllite-0.5.1.dist-info/LICENSE
rllite-0.5.1.dist-info/METADATA
rllite-0.5.1.dist-info/WHEEL
rllite-0.5.1.dist-info/top_level.txt
rllite-0.5.1.dist-info/RECORD
